{"__symbolic":"module","version":4,"metadata":{"WizardTabTitle":{"__symbolic":"class","decorators":[{"__symbolic":"call","expression":{"__symbolic":"reference","module":"@angular/core","name":"Directive","line":20,"character":1},"arguments":[{"selector":"ng-template[wizardTabTitle]"}]}],"members":{"__ctor__":[{"__symbolic":"constructor","parameters":[{"__symbolic":"reference","name":"TemplateRef","module":"@angular/core","arguments":[{"__symbolic":"reference","name":"any"}]}]}]}},"WizardTabContent":{"__symbolic":"class","decorators":[{"__symbolic":"call","expression":{"__symbolic":"reference","module":"@angular/core","name":"Directive","line":28,"character":1},"arguments":[{"selector":"ng-template[wizardTabContent]"}]}],"members":{"__ctor__":[{"__symbolic":"constructor","parameters":[{"__symbolic":"reference","name":"TemplateRef","module":"@angular/core","arguments":[{"__symbolic":"reference","name":"any"}]}]}]}},"WizardTab":{"__symbolic":"class","decorators":[{"__symbolic":"call","expression":{"__symbolic":"reference","module":"@angular/core","name":"Directive","line":36,"character":1},"arguments":[{"selector":"wizard-tab"}]}],"members":{"id":[{"__symbolic":"property","decorators":[{"__symbolic":"call","expression":{"__symbolic":"reference","module":"@angular/core","name":"Input","line":41,"character":3}}]}],"title":[{"__symbolic":"property","decorators":[{"__symbolic":"call","expression":{"__symbolic":"reference","module":"@angular/core","name":"Input","line":45,"character":3}}]}],"complete":[{"__symbolic":"property","decorators":[{"__symbolic":"call","expression":{"__symbolic":"reference","module":"@angular/core","name":"Input","line":49,"character":3}}]}],"contentTpl":[{"__symbolic":"property","decorators":[{"__symbolic":"call","expression":{"__symbolic":"reference","module":"@angular/core","name":"ContentChild","line":52,"character":3},"arguments":[{"__symbolic":"reference","name":"WizardTabContent"}]}]}],"titleTpl":[{"__symbolic":"property","decorators":[{"__symbolic":"call","expression":{"__symbolic":"reference","module":"@angular/core","name":"ContentChild","line":53,"character":3},"arguments":[{"__symbolic":"reference","name":"WizardTabTitle"}]}]}],"__ctor__":[{"__symbolic":"constructor"}]}},"WizardChangeEvent":{"__symbolic":"interface"},"WizardTabset":{"__symbolic":"class","decorators":[{"__symbolic":"call","expression":{"__symbolic":"reference","module":"@angular/core","name":"Component","line":83,"character":1},"arguments":[{"selector":"wizard-tabset","exportAs":"wizardTabset","styles":["\n    .wizard {\n      margin: 0;\n      padding: 0;\n      list-style: none;\n    }\n    .wizard-wrap-horizontal .wizard {\n      display: table;\n      width: 75%;\n      margin: 0 auto;\n      margin-bottom: 10px;\n    }\n    .wizard-wrap-horizontal .wizard .wizard-item {\n      display: table-cell;\n      list-style-type: none;\n      position: relative;\n      vertical-align: top;\n    }\n    .wizard-wrap-vertical {\n      display: table;\n      width: 100%;\n      position: relative;\n      margin-bottom: 20px;\n    }\n    .wizard-wrap-vertical .wizard {\n      display: table-cell;\n      vertical-align: middle;\n      width: 100px;\n    }\n    .wizard-wrap-vertical .wizard .wizard-item {\n      display: inline-block;\n      list-style-type: none;\n      position: relative;\n    }\n    .wizard-wrap-vertical .wizard-content {\n      display: table-cell;\n    }\n    .wizard-vertical .wizard-item {\n      width: 100px;\n    }\n    .wizard .wizard-item .wizard-link {\n      display: block;\n      position: relative;\n      cursor: text;\n    }\n    .wizard-vertical .wizard-item .wizard-link {\n      padding-bottom: 2rem;\n    }\n    .wizard-vertical .wizard-item:first-child .wizard-link {\n      padding-top: 2rem;\n    }\n    .wizard .wizard-item .wizard-link:after {\n      content: \"\";\n      position: absolute;\n      background-color: #ededed;\n    }\n    .wizard-horizontal .wizard-item .wizard-link:after {\n      width: 100%;\n      height: 1px;\n      left: 0;\n      top: 16px;\n    }\n    .wizard-vertical .wizard-item .wizard-link:after {\n      width: 1px;\n      height: 100%;\n      left: 16px;\n      top: 0px;\n    }\n    .wizard .wizard-item .wizard-link:hover {\n      text-decoration: none;\n    }\n    .wizard .wizard-item .wizard-link .wizard-count-wrap {\n      text-align: center;\n      margin-bottom: 8px;\n    }\n    .wizard .wizard-item .wizard-link .wizard-title-text-wrap {\n      color: #3f3f3f;\n      text-align: center;\n    }\n    .wizard-vertical .wizard-item .wizard-link .wizard-count-wrap, .wizard-vertical .wizard-item .wizard-link .wizard-title-text-wrap {\n      display: inline-block;\n      margin-bottom: 0;\n      margin-right: 8px;\n\n    }\n    .wizard .wizard-item .wizard-link .wizard-count-wrap .wizard-count {\n      color: #474747;\n      background: #ededed;\n      width: 32px;\n      height: 32px;\n      display: inline-block;\n      border: 1px solid #ededed;\n      line-height: 30px;\n      border-radius: 50%;\n      position: relative;\n      text-align: center;\n      z-index: 99;\n    }\n    .wizard .wizard-item .wizard-link.active .wizard-count-wrap .wizard-count {\n      background: #007ac3;\n      color: #fff;\n    }\n    .wizard .wizard-item .wizard-link.complete .wizard-count-wrap .wizard-count {\n      color: #fff;\n      background: #85bc20;\n    }\n    .wizard-content {\n      background-color: #ededed;\n      width: 100%;\n      min-height: 400px;\n      margin-bottom: 20px;\n    }\n    .wizard-content .wizard-pane {\n      padding: 20px;\n    }\n    .wizard-title-text-wrap {\n      position: relative;\n      z-index: 99;\n    }\n    @media (max-width: 350px) {\n      .wizard-vertical .wizard-item {\n        width: 70px;\n      }\n    }\n    .wk-wizard-finish-later,\n.wk-wizard-cancel {\n  padding-left: 0.75rem !important;\n  position: unset !important;\n}\n\n.wk-wizard-prev-step {\n  position: relative;\n  padding-left: 50px;\n  &[disabled] {\n    cursor: not-allowed;\n    background-color: #dadada !important;\n    color: black !important;\n    border-color: #dadada !important;\n    .coomonglyphs {\n      background-color: rgba(255, 255, 255, .2);\n      border-color: rgba(255, 255, 255, .2);\n    }\n    &:hover {\n      background-color: #bfbfbf !important;\n      border-color: #bfbfbf !important;\n    }\n  }\n  .commonglyphs {\n    position: absolute;\n    left: -1px;\n    top: -1px;\n    padding: 0.375rem 0.75rem;\n    background-color: rgba(255, 255, 255, .2);\n    border-color: rgba(255, 255, 255, .2);\n    height: 35px;\n  }\n}\n  "],"template":"\n  <div [class]=\"'wizard-wrap-' + orientation\">\n      <ul [class]=\"'wizard wizard-' + orientation\">\n          <li class=\"wizard-item\" *ngFor=\"let tab of tabs; let i = index;\">\n              <a [id]=\"tab.id\" class=\"wizard-link\" (click)=\"$event.preventDefault();\" [class.complete]=\"tab.complete\" [class.active]=\"tab.id === activeId\" href>\n                  <div class=\"wizard-count-wrap\">\n                      <span class=\"wizard-count\" *ngIf=\"!tab.complete\">{{i + 1}}</span>\n                      <span class=\"wizard-count\" *ngIf=\"tab.complete\" (click)=\"_goToThisStep(tab.id)\">\n                          <span class=\"commonglyphs commonglyphs-check\"></span>\n                      </span>\n                  </div>\n                  <div class=\"wizard-title-text-wrap\">\n                      <span class=\"wizard-title-text\">\n                          {{tab.title}}\n                          <ng-template [ngTemplateOutlet]=\"tab.titleTpl?.templateRef\"></ng-template>\n                      </span>\n                  </div>\n              </a>\n          </li>\n      </ul>\n      <div class=\"wizard-content\">\n          <ng-template ngFor let-tab [ngForOf]=\"tabs\">\n              <div class=\"wizard-pane {{tab.id === activeId ? 'active' : null}}\" *ngIf=\"tab.id === activeId\">\n                  <ng-template [ngTemplateOutlet]=\"tab.contentTpl.templateRef\"></ng-template>\n              </div>\n          </ng-template>\n      </div>\n  </div>\n  <div class=\"text-right\" *ngIf=\"showButtons\">\n      <button type=\"button\" class=\"btn btn-default cancel-step\" [disabled]=\"!isNotFirst()\" (click)=\"cancelStep()\">Cancel</button>\n      <button type=\"button\" class=\"btn btn-default\" [disabled]=\"!isNotFirst()\" (click)=\"finishLaterStep()\">Finish Later</button>\n      <button type=\"button\" class=\"btn btn-default prev-step\" [disabled]=\"!isNotFirst()\" (click)=\"prevStep()\">\n          <span class=\"commonglyphs commonglyphs-arrow-left\"></span>Previous\n      </button>\n      <button type=\"button\" class=\"btn btn-primary next-step\" *ngIf=\"!isLastStep()\" (click)=\"nextStep()\">\n          Next\n          <span class=\"commonglyphs commonglyphs-arrow-right\"></span>\n      </button>\n      <button type=\"button\" class=\"btn btn-primary submit-step\" *ngIf=\"isLastStep()\" (click)=\"submitStep()\">Finish</button>\n  </div>\n  <ng-template #content let-c=\"close\" let-d=\"dismiss\">\n      <div class=\"modal-header\">\n          <h4 class=\"modal-title\">Wizard</h4>\n          <span class=\"commonglyphs commonglyphs-close pull-right modal-close\" aria-label=\"Close\" (click)=\"d('Cross click')\"></span>\n      </div>\n      <div class=\"modal-body\">\n          <p>Your data will be lost, do you still want to cancel?</p>\n      </div>\n      <div class=\"modal-footer\">\n          <button class=\"btn btn-secondary\" type=\"button\" (click)=\"d('Close click')\">No</button>\n          <button class=\"btn btn-primary\" type=\"button\" (click)=\"c('Close click')\">Yes</button>\n      </div>\n  </ng-template>\n  "}]}],"members":{"showButtons":[{"__symbolic":"property","decorators":[{"__symbolic":"call","expression":{"__symbolic":"reference","module":"@angular/core","name":"Input","line":301,"character":3}}]}],"tabs":[{"__symbolic":"property","decorators":[{"__symbolic":"call","expression":{"__symbolic":"reference","module":"@angular/core","name":"ContentChildren","line":304,"character":3},"arguments":[{"__symbolic":"reference","name":"WizardTab"}]}]}],"activeId":[{"__symbolic":"property","decorators":[{"__symbolic":"call","expression":{"__symbolic":"reference","module":"@angular/core","name":"Input","line":309,"character":3}}]}],"orientation":[{"__symbolic":"property","decorators":[{"__symbolic":"call","expression":{"__symbolic":"reference","module":"@angular/core","name":"Input","line":315,"character":3}}]}],"wizardChange":[{"__symbolic":"property","decorators":[{"__symbolic":"call","expression":{"__symbolic":"reference","module":"@angular/core","name":"Output","line":320,"character":3}}]}],"nextHandler":[{"__symbolic":"property","decorators":[{"__symbolic":"call","expression":{"__symbolic":"reference","module":"@angular/core","name":"Output","line":325,"character":3}}]}],"prevHandler":[{"__symbolic":"property","decorators":[{"__symbolic":"call","expression":{"__symbolic":"reference","module":"@angular/core","name":"Output","line":330,"character":3}}]}],"finishLaterHandler":[{"__symbolic":"property","decorators":[{"__symbolic":"call","expression":{"__symbolic":"reference","module":"@angular/core","name":"Output","line":335,"character":3}}]}],"submitHandler":[{"__symbolic":"property","decorators":[{"__symbolic":"call","expression":{"__symbolic":"reference","module":"@angular/core","name":"Output","line":340,"character":3}}]}],"cancelHandler":[{"__symbolic":"property","decorators":[{"__symbolic":"call","expression":{"__symbolic":"reference","module":"@angular/core","name":"Output","line":345,"character":3}}]}],"content":[{"__symbolic":"property","decorators":[{"__symbolic":"call","expression":{"__symbolic":"reference","module":"@angular/core","name":"ViewChild","line":347,"character":3},"arguments":["content"]}]}],"__ctor__":[{"__symbolic":"constructor","parameters":[{"__symbolic":"reference","module":"@ng-bootstrap/ng-bootstrap","name":"NgbModal","line":350,"character":36}]}],"select":[{"__symbolic":"method"}],"_goToThisStep":[{"__symbolic":"method"}],"isLastStep":[{"__symbolic":"method"}],"isNotFirst":[{"__symbolic":"method"}],"nextStep":[{"__symbolic":"method"}],"prevStep":[{"__symbolic":"method"}],"submitStep":[{"__symbolic":"method"}],"finishLaterStep":[{"__symbolic":"method"}],"cancelStep":[{"__symbolic":"method"}],"getDismissReason":[{"__symbolic":"method"}],"ngAfterContentChecked":[{"__symbolic":"method"}],"_getTabById":[{"__symbolic":"method"}]}},"WizardTabsetModule":{"__symbolic":"class","decorators":[{"__symbolic":"call","expression":{"__symbolic":"reference","module":"@angular/core","name":"NgModule","line":15,"character":1},"arguments":[{"declarations":[{"__symbolic":"reference","name":"WizardTabset"},{"__symbolic":"reference","name":"WizardTab"},{"__symbolic":"reference","name":"WizardTabContent"},{"__symbolic":"reference","name":"WizardTabTitle"}],"exports":[{"__symbolic":"reference","name":"WizardTabset"},{"__symbolic":"reference","name":"WizardTab"},{"__symbolic":"reference","name":"WizardTabContent"},{"__symbolic":"reference","name":"WizardTabTitle"}],"imports":[{"__symbolic":"reference","module":"@angular/common","name":"CommonModule","line":19,"character":4},{"__symbolic":"call","expression":{"__symbolic":"select","expression":{"__symbolic":"reference","module":"@ng-bootstrap/ng-bootstrap","name":"NgbModalModule","line":20,"character":4},"member":"forRoot"}}]}]}],"members":{},"statics":{"forRoot":{"__symbolic":"function","parameters":[],"value":{"ngModule":{"__symbolic":"reference","name":"WizardTabsetModule"}}}}}},"origins":{"WizardTabTitle":"./lib/wk-wizard.component","WizardTabContent":"./lib/wk-wizard.component","WizardTab":"./lib/wk-wizard.component","WizardChangeEvent":"./lib/wk-wizard.component","WizardTabset":"./lib/wk-wizard.component","WizardTabsetModule":"./lib/wk-wizard.module"},"importAs":"wk-wizard"}